pastel/__init__.py
pastel/pastel.py
pastel/stack.py
pastel/style.py
pastel/version.py
pastel-0.1.0.dist-info/DESCRIPTION.rst
pastel-0.1.0.dist-info/METADATA
pastel-0.1.0.dist-info/RECORD
pastel-0.1.0.dist-info/WHEEL
pastel-0.1.0.dist-info/metadata.json
pastel-0.1.0.dist-info/top_level.txt
